LICENSE
README.md
setup.py
pytest_tools/__init__.py
pytest_tools/assert_does_not_raise.py
pytest_tools.egg-info/PKG-INFO
pytest_tools.egg-info/SOURCES.txt
pytest_tools.egg-info/dependency_links.txt
pytest_tools.egg-info/requires.txt
pytest_tools.egg-info/top_level.txt
tests/__init__.py
tests/test_assert_does_not_raised.py